[
    {
        "title": "KU Hackathon",
        "description": "ร่วมกันระดมความคิดแก้ไขปัญหาต่าง ๆ ภายในมหาวิทยาลัยด้วยเทคโนโลยี"
    },
    {
        "title": "KU Tech Camp",
        "description": "ออกค่ายโรงเรียนมัธยมเพื่อสอนน้องด้านโค้ดเบื้องต้น"
    },
    {
        "title": "KU Tech Talk",
        "description": "การเสวนาทางวิชาการ ในหัวข้อด้านเทคโนโลยีที่น่าสนใจในปัจจุบัน และเป็นประโยชน์ในทุกคณะ, สาขา"
    },
    {
        "title": "KU Mini Bar Camp",
        "description": "ร่วมพูดคุย-แลกเปลี่ยนในหัวข้อ และประเด็นที่น่าสนใจภายในสมาชิกกลุ่มกิจกรรม"
    }
]
  